ShowTkProssBar/ShowTkProssBar.py
ShowTkProssBar/__init__.py
ShowTkProssBar-0.0.4.dist-info/LICENSE
ShowTkProssBar-0.0.4.dist-info/METADATA
ShowTkProssBar-0.0.4.dist-info/WHEEL
ShowTkProssBar-0.0.4.dist-info/top_level.txt
ShowTkProssBar-0.0.4.dist-info/RECORD
