Metadata-Version: 2.1
Name: ShowTkProssBar
Version: 0.0.4
Summary: show a tk prossbar
Home-page: https://44202439.org
Author: glwwanggs
Author-email: 442024339@qq.com
License: MIT
Platform: UNKNOWN
